Metadata-Version: 2.1
Name: neat-python-gicminos
Version: 0.96
Summary: A NEAT (NeuroEvolution of Augmenting Topologies) implementation
Home-page: https://github.com/Gicminos/neat-python
Author: cesar.gomes, mirrorballu2
Author-email: nobody@nowhere.com
Maintainer: Gicminos
Maintainer-email: nobody@nowhere.com
License: BSD
Platform: UNKNOWN
Classifier: Development Status :: 4 - Beta
Classifier: Intended Audience :: Developers
Classifier: Intended Audience :: Education
Classifier: Intended Audience :: Science/Research
Classifier: License :: OSI Approved :: BSD License
Classifier: Operating System :: OS Independent
Classifier: Programming Language :: Python :: 2.7
Classifier: Programming Language :: Python :: 3.3
Classifier: Programming Language :: Python :: 3.4
Classifier: Programming Language :: Python :: 3.5
Classifier: Programming Language :: Python :: 3.6
Classifier: Programming Language :: Python :: 3.7
Classifier: Programming Language :: Python :: 3.8
Classifier: Programming Language :: Python :: 3.9
Classifier: Programming Language :: Python :: Implementation :: PyPy
Classifier: Topic :: Scientific/Engineering
